{
  "questionId": "js-add-strings",
  "version": 1,
  "defaultKey": "approach1",
  "variants": {
    "approach1": {
      "language": "javascript",
      "code": "export default function addStrings(a, b) {\n  let i = a.length - 1;\n  let j = b.length - 1;\n  let carry = 0;\n  const out = [];\n\n  while (i >= 0 || j >= 0 || carry) {\n    const da = i >= 0 ? a.charCodeAt(i) - 48 : 0;\n    const db = j >= 0 ? b.charCodeAt(j) - 48 : 0;\n    const sum = da + db + carry;\n    out.push(String(sum % 10));\n    carry = Math.floor(sum / 10);\n    i--;\n    j--;\n  }\n\n  return out.reverse().join('');\n}\n",
      "nodes": [
        {
          "id": "d1-start-from-right",
          "title": "Start from the rightmost digits",
          "anchor": {
            "lineStart": 2,
            "lineEnd": 4,
            "snippet": "let i = a.length - 1;"
          },
          "why": "Addition works from right to left, so we mirror how people do it on paper.",
          "alternative": "Pad both strings to same length, then loop left to right.",
          "tradeoff": "Two pointers are simple and avoid creating padded copies."
        },
        {
          "id": "d2-loop-until-carry-done",
          "title": "Keep looping while carry still exists",
          "anchor": {
            "lineStart": 7,
            "lineEnd": 7,
            "snippet": "while (i >= 0 || j >= 0 || carry) {"
          },
          "why": "Even when both strings end, we might still need one extra digit from carry.",
          "alternative": "Loop only while i or j is valid, then append carry separately.",
          "tradeoff": "Single condition is cleaner and handles all cases in one loop."
        },
        {
          "id": "d3-charcode-to-digit",
          "title": "Read each character as a digit",
          "anchor": {
            "lineStart": 8,
            "lineEnd": 9,
            "snippet": "a.charCodeAt(i) - 48"
          },
          "why": "This converts numeric characters to numbers without parsing whole strings.",
          "alternative": "Use Number(a[i]) and Number(b[j]).",
          "tradeoff": "charCode is a bit lower-level but usually faster in tight loops."
        },
        {
          "id": "d4-split-digit-and-carry",
          "title": "Split sum into digit and next carry",
          "anchor": {
            "lineStart": 10,
            "lineEnd": 12,
            "snippet": "const sum = da + db + carry;"
          },
          "why": "sum % 10 is the current digit, and floor(sum / 10) is the carry for the next step.",
          "alternative": "Use string math helpers for every step.",
          "tradeoff": "Modulo/floor math is direct and keeps the code short."
        },
        {
          "id": "d5-build-reversed-then-flip",
          "title": "Build in reverse, then flip once",
          "anchor": {
            "lineStart": 11,
            "lineEnd": 17,
            "snippet": "return out.reverse().join('');"
          },
          "why": "We discover digits from least-significant to most-significant, so reversing once gives correct order.",
          "alternative": "Prepend each digit to a string every iteration.",
          "tradeoff": "Array + one reverse is usually more efficient than repeated string prepends."
        }
      ]
    }
  }
}
